acad_iot/__init__.py
acad_iot/anomaly_detection.py
acad_iot/clustering.py
acad_iot/data_preprocessing.py
acad_iot/dimensionality_reduction.py
acad_iot/visualization.py
acad_iot-0.1.0.dist-info/License.txt
acad_iot-0.1.0.dist-info/METADATA
acad_iot-0.1.0.dist-info/WHEEL
acad_iot-0.1.0.dist-info/top_level.txt
acad_iot-0.1.0.dist-info/RECORD
